build/__init__.py
build/main.py
KaganKucukPortfolio-0.0.1.dist-info/METADATA
KaganKucukPortfolio-0.0.1.dist-info/WHEEL
KaganKucukPortfolio-0.0.1.dist-info/top_level.txt
KaganKucukPortfolio-0.0.1.dist-info/RECORD
