Metadata-Version: 2.1
Name: KaganKucukPortfolio
Version: 0.0.1
Summary: Portfolio page
Home-page: UNKNOWN
Author: Mustafa ali kağan Küçük
Author-email: <mustafa.ali.kagan@gmail.com>
License: UNKNOWN
Keywords: python,video,stream,video stream,camera stream,sockets
Platform: UNKNOWN
Classifier: Development Status :: 1 - Planning
Classifier: Intended Audience :: Developers
Classifier: Programming Language :: Python :: 3
Classifier: Operating System :: Unix
Classifier: Operating System :: MacOS :: MacOS X
Classifier: Operating System :: Microsoft :: Windows
Requires-Dist: opencv-python
Requires-Dist: pyautogui
Requires-Dist: pyaudio
